{
  "task": "acdc_lv",
  "fm": "dinov2_vitb14",
  "seed": 44,
  "n_test": 361,
  "test_ids": [
    "patient003_frame01_slice000",
    "patient003_frame01_slice001",
    "patient003_frame01_slice002",
    "patient003_frame01_slice003",
    "patient003_frame01_slice004",
    "patient003_frame01_slice005",
    "patient003_frame01_slice006",
    "patient003_frame01_slice007",
    "patient003_frame01_slice008",
    "patient003_frame01_slice009",
    "patient003_frame15_slice000",
    "patient003_frame15_slice001",
    "patient003_frame15_slice002",
    "patient003_frame15_slice003",
    "patient003_frame15_slice004",
    "patient003_frame15_slice005",
    "patient003_frame15_slice006",
    "patient003_frame15_slice007",
    "patient003_frame15_slice008",
    "patient003_frame15_slice009",
    "patient005_frame01_slice000",
    "patient005_frame01_slice001",
    "patient005_frame01_slice002",
    "patient005_frame01_slice003",
    "patient005_frame01_slice004",
    "patient005_frame01_slice005",
    "patient005_frame01_slice006",
    "patient005_frame01_slice007",
    "patient005_frame01_slice008",
    "patient005_frame01_slice009",
    "patient005_frame13_slice000",
    "patient005_frame13_slice001",
    "patient005_frame13_slice002",
    "patient005_frame13_slice003",
    "patient005_frame13_slice004",
    "patient005_frame13_slice005",
    "patient005_frame13_slice006",
    "patient005_frame13_slice007",
    "patient005_frame13_slice008",
    "patient005_frame13_slice009",
    "patient019_frame01_slice000",
    "patient019_frame01_slice001",
    "patient019_frame01_slice002",
    "patient019_frame01_slice003",
    "patient019_frame01_slice004",
    "patient019_frame01_slice005",
    "patient019_frame01_slice006",
    "patient019_frame01_slice007",
    "patient019_frame01_slice008",
    "patient019_frame01_slice009",
    "patient019_frame01_slice010",
    "patient019_frame11_slice000",
    "patient019_frame11_slice001",
    "patient019_frame11_slice002",
    "patient019_frame11_slice003",
    "patient019_frame11_slice004",
    "patient019_frame11_slice005",
    "patient019_frame11_slice006",
    "patient019_frame11_slice007",
    "patient019_frame11_slice008",
    "patient019_frame11_slice009",
    "patient022_frame01_slice000",
    "patient022_frame01_slice001",
    "patient022_frame01_slice002",
    "patient022_frame01_slice003",
    "patient022_frame01_slice004",
    "patient022_frame01_slice005",
    "patient022_frame01_slice006",
    "patient022_frame11_slice000",
    "patient022_frame11_slice001",
    "patient022_frame11_slice002",
    "patient022_frame11_slice003",
    "patient022_frame11_slice004",
    "patient022_frame11_slice005",
    "patient022_frame11_slice006",
    "patient025_frame01_slice000",
    "patient025_frame01_slice001",
    "patient025_frame01_slice002",
    "patient025_frame01_slice003",
    "patient025_frame01_slice004",
    "patient025_frame01_slice005",
    "patient025_frame01_slice006",
    "patient025_frame01_slice007",
    "patient025_frame01_slice008",
    "patient025_frame09_slice000",
    "patient025_frame09_slice001",
    "patient025_frame09_slice002",
    "patient025_frame09_slice003",
    "patient025_frame09_slice004",
    "patient025_frame09_slice005",
    "patient025_frame09_slice006",
    "patient025_frame09_slice007",
    "patient025_frame09_slice008",
    "patient026_frame01_slice000",
    "patient026_frame01_slice001",
    "patient026_frame01_slice002",
    "patient026_frame01_slice003",
    "patient026_frame01_slice004",
    "patient026_frame01_slice005",
    "patient026_frame01_slice006",
    "patient026_frame01_slice007",
    "patient026_frame01_slice008",
    "patient026_frame01_slice009",
    "patient026_frame12_slice001",
    "patient026_frame12_slice002",
    "patient026_frame12_slice003",
    "patient026_frame12_slice004",
    "patient026_frame12_slice005",
    "patient026_frame12_slice006",
    "patient026_frame12_slice007",
    "patient026_frame12_slice008",
    "patient028_frame01_slice000",
    "patient028_frame01_slice001",
    "patient028_frame01_slice002",
    "patient028_frame01_slice003",
    "patient028_frame01_slice004",
    "patient028_frame01_slice005",
    "patient028_frame01_slice006",
    "patient028_frame01_slice007",
    "patient028_frame01_slice008",
    "patient028_frame09_slice000",
    "patient028_frame09_slice001",
    "patient028_frame09_slice002",
    "patient028_frame09_slice003",
    "patient028_frame09_slice004",
    "patient028_frame09_slice005",
    "patient028_frame09_slice006",
    "patient034_frame01_slice000",
    "patient034_frame01_slice001",
    "patient034_frame01_slice002",
    "patient034_frame01_slice003",
    "patient034_frame01_slice004",
    "patient034_frame01_slice005",
    "patient034_frame01_slice006",
    "patient034_frame01_slice007",
    "patient034_frame01_slice008",
    "patient034_frame01_slice009",
    "patient034_frame16_slice000",
    "patient034_frame16_slice001",
    "patient034_frame16_slice002",
    "patient034_frame16_slice003",
    "patient034_frame16_slice004",
    "patient034_frame16_slice005",
    "patient034_frame16_slice006",
    "patient034_frame16_slice007",
    "patient034_frame16_slice008",
    "patient043_frame01_slice000",
    "patient043_frame01_slice001",
    "patient043_frame01_slice002",
    "patient043_frame01_slice003",
    "patient043_frame01_slice004",
    "patient043_frame01_slice005",
    "patient043_frame01_slice006",
    "patient043_frame01_slice007",
    "patient043_frame01_slice008",
    "patient043_frame01_slice009",
    "patient043_frame01_slice010",
    "patient043_frame01_slice011",
    "patient043_frame07_slice000",
    "patient043_frame07_slice001",
    "patient043_frame07_slice002",
    "patient043_frame07_slice003",
    "patient043_frame07_slice004",
    "patient043_frame07_slice005",
    "patient043_frame07_slice006",
    "patient043_frame07_slice007",
    "patient043_frame07_slice008",
    "patient043_frame07_slice009",
    "patient043_frame07_slice010",
    "patient043_frame07_slice011",
    "patient051_frame01_slice000",
    "patient051_frame01_slice001",
    "patient051_frame01_slice002",
    "patient051_frame01_slice003",
    "patient051_frame01_slice004",
    "patient051_frame01_slice005",
    "patient051_frame01_slice006",
    "patient051_frame01_slice007",
    "patient051_frame01_slice008",
    "patient051_frame01_slice009",
    "patient051_frame11_slice001",
    "patient051_frame11_slice002",
    "patient051_frame11_slice003",
    "patient051_frame11_slice004",
    "patient051_frame11_slice005",
    "patient051_frame11_slice006",
    "patient051_frame11_slice007",
    "patient051_frame11_slice008",
    "patient051_frame11_slice009",
    "patient052_frame01_slice000",
    "patient052_frame01_slice001",
    "patient052_frame01_slice002",
    "patient052_frame01_slice003",
    "patient052_frame01_slice004",
    "patient052_frame01_slice005",
    "patient052_frame01_slice006",
    "patient052_frame01_slice007",
    "patient052_frame09_slice000",
    "patient052_frame09_slice001",
    "patient052_frame09_slice002",
    "patient052_frame09_slice003",
    "patient052_frame09_slice004",
    "patient052_frame09_slice005",
    "patient052_frame09_slice006",
    "patient052_frame09_slice007",
    "patient053_frame01_slice000",
    "patient053_frame01_slice001",
    "patient053_frame01_slice002",
    "patient053_frame01_slice003",
    "patient053_frame01_slice004",
    "patient053_frame01_slice005",
    "patient053_frame01_slice006",
    "patient053_frame12_slice000",
    "patient053_frame12_slice001",
    "patient053_frame12_slice002",
    "patient053_frame12_slice003",
    "patient053_frame12_slice004",
    "patient053_frame12_slice005",
    "patient053_frame12_slice006",
    "patient057_frame01_slice000",
    "patient057_frame01_slice001",
    "patient057_frame01_slice002",
    "patient057_frame01_slice003",
    "patient057_frame01_slice004",
    "patient057_frame01_slice005",
    "patient057_frame01_slice006",
    "patient057_frame01_slice007",
    "patient057_frame09_slice000",
    "patient057_frame09_slice001",
    "patient057_frame09_slice002",
    "patient057_frame09_slice003",
    "patient057_frame09_slice004",
    "patient057_frame09_slice005",
    "patient057_frame09_slice006",
    "patient060_frame01_slice000",
    "patient060_frame01_slice001",
    "patient060_frame01_slice002",
    "patient060_frame01_slice003",
    "patient060_frame01_slice004",
    "patient060_frame01_slice005",
    "patient060_frame01_slice006",
    "patient060_frame01_slice007",
    "patient060_frame01_slice008",
    "patient060_frame14_slice001",
    "patient060_frame14_slice002",
    "patient060_frame14_slice003",
    "patient060_frame14_slice004",
    "patient060_frame14_slice005",
    "patient060_frame14_slice006",
    "patient060_frame14_slice007",
    "patient060_frame14_slice008",
    "patient062_frame01_slice000",
    "patient062_frame01_slice001",
    "patient062_frame01_slice002",
    "patient062_frame01_slice003",
    "patient062_frame01_slice004",
    "patient062_frame01_slice005",
    "patient062_frame01_slice006",
    "patient062_frame01_slice007",
    "patient062_frame01_slice008",
    "patient062_frame01_slice009",
    "patient062_frame09_slice000",
    "patient062_frame09_slice001",
    "patient062_frame09_slice002",
    "patient062_frame09_slice003",
    "patient062_frame09_slice004",
    "patient062_frame09_slice005",
    "patient062_frame09_slice006",
    "patient062_frame09_slice007",
    "patient062_frame09_slice008",
    "patient072_frame01_slice000",
    "patient072_frame01_slice001",
    "patient072_frame01_slice002",
    "patient072_frame01_slice003",
    "patient072_frame01_slice004",
    "patient072_frame01_slice005",
    "patient072_frame01_slice006",
    "patient072_frame11_slice000",
    "patient072_frame11_slice001",
    "patient072_frame11_slice002",
    "patient072_frame11_slice003",
    "patient072_frame11_slice004",
    "patient072_frame11_slice005",
    "patient072_frame11_slice006",
    "patient082_frame01_slice000",
    "patient082_frame01_slice001",
    "patient082_frame01_slice002",
    "patient082_frame01_slice003",
    "patient082_frame01_slice004",
    "patient082_frame01_slice005",
    "patient082_frame01_slice006",
    "patient082_frame01_slice007",
    "patient082_frame01_slice008",
    "patient082_frame01_slice009",
    "patient082_frame01_slice010",
    "patient082_frame01_slice011",
    "patient082_frame01_slice012",
    "patient082_frame01_slice013",
    "patient082_frame01_slice014",
    "patient082_frame01_slice015",
    "patient082_frame07_slice000",
    "patient082_frame07_slice001",
    "patient082_frame07_slice002",
    "patient082_frame07_slice003",
    "patient082_frame07_slice004",
    "patient082_frame07_slice005",
    "patient082_frame07_slice006",
    "patient082_frame07_slice007",
    "patient082_frame07_slice008",
    "patient082_frame07_slice009",
    "patient082_frame07_slice010",
    "patient082_frame07_slice011",
    "patient082_frame07_slice012",
    "patient082_frame07_slice013",
    "patient082_frame07_slice014",
    "patient082_frame07_slice015",
    "patient093_frame01_slice000",
    "patient093_frame01_slice001",
    "patient093_frame01_slice002",
    "patient093_frame01_slice003",
    "patient093_frame01_slice004",
    "patient093_frame01_slice005",
    "patient093_frame01_slice006",
    "patient093_frame01_slice007",
    "patient093_frame01_slice008",
    "patient093_frame14_slice001",
    "patient093_frame14_slice002",
    "patient093_frame14_slice003",
    "patient093_frame14_slice004",
    "patient093_frame14_slice005",
    "patient093_frame14_slice006",
    "patient093_frame14_slice007",
    "patient093_frame14_slice008",
    "patient098_frame01_slice000",
    "patient098_frame01_slice001",
    "patient098_frame01_slice002",
    "patient098_frame01_slice003",
    "patient098_frame01_slice004",
    "patient098_frame01_slice005",
    "patient098_frame01_slice006",
    "patient098_frame09_slice000",
    "patient098_frame09_slice001",
    "patient098_frame09_slice002",
    "patient098_frame09_slice003",
    "patient098_frame09_slice004",
    "patient098_frame09_slice005",
    "patient098_frame09_slice006",
    "patient100_frame01_slice000",
    "patient100_frame01_slice001",
    "patient100_frame01_slice002",
    "patient100_frame01_slice003",
    "patient100_frame01_slice004",
    "patient100_frame01_slice005",
    "patient100_frame01_slice006",
    "patient100_frame13_slice000",
    "patient100_frame13_slice001",
    "patient100_frame13_slice002",
    "patient100_frame13_slice003",
    "patient100_frame13_slice004",
    "patient100_frame13_slice005",
    "patient100_frame13_slice006"
  ],
  "per_case_dice": [
    0.679929256439209,
    0.8732280135154724,
    0.7906197905540466,
    0.8160919547080994,
    0.9474548697471619,
    0.8517646789550781,
    0.897487461566925,
    0.8501694798469543,
    0.7706122398376465,
    0.5494505763053894,
    0.6796326041221619,
    0.8283281326293945,
    0.8736559152603149,
    0.7943621277809143,
    0.9001243114471436,
    0.865061342716217,
    0.9147928953170776,
    0.8878127336502075,
    0.7622504830360413,
    0.5742574334144592,
    0.7591406106948853,
    0.8508192300796509,
    0.8745439052581787,
    0.8729832768440247,
    0.9310664534568787,
    0.9430676698684692,
    0.8737024068832397,
    0.8837696313858032,
    0.8561816811561584,
    0.712909460067749,
    0.6985645890235901,
    0.7496812343597412,
    0.8808885216712952,
    0.8820479512214661,
    0.8683651685714722,
    0.8930765986442566,
    0.9135695695877075,
    0.9274145364761353,
    0.8636734485626221,
    0.3401360511779785,
    0.9169074892997742,
    0.9443978667259216,
    0.892119824886322,
    0.9100243449211121,
    0.9303555488586426,
    0.9053522944450378,
    0.9432623982429504,
    0.8898857831954956,
    0.8584850430488586,
    0.7949044704437256,
    0.0,
    0.8352941274642944,
    0.9252524971961975,
    0.8986117243766785,
    0.9423143267631531,
    0.9632925391197205,
    0.8987477421760559,
    0.9040358662605286,
    0.8453947305679321,
    0.8516746163368225,
    0.7638036608695984,
    0.9111579060554504,
    0.9167943000793457,
    0.9028651118278503,
    0.6699029207229614,
    0.0,
    0.2448979616165161,
    0.0,
    0.8322295546531677,
    0.8100628852844238,
    0.20967741310596466,
    0.0,
    0.0,
    0.05714285746216774,
    0.0,
    0.8891891837120056,
    0.7655430436134338,
    0.9010238647460938,
    0.75,
    0.8686296939849854,
    0.8942639827728271,
    0.8992629051208496,
    0.3030303120613098,
    0.8296703100204468,
    0.8133333325386047,
    0.6553846001625061,
    0.7356076836585999,
    0.6677471399307251,
    0.6968085169792175,
    0.8617234230041504,
    0.0,
    0.0,
    0.40909090638160706,
    0.7269772291183472,
    0.685834527015686,
    0.9117351770401001,
    0.4597875475883484,
    0.8107049465179443,
    0.569243848323822,
    0.7236180901527405,
    0.8297872543334961,
    0.4586776793003082,
    0.6666666865348816,
    0.74956214427948,
    0.8871251940727234,
    0.4877505600452423,
    0.4103260934352875,
    0.8066825866699219,
    0.09282700717449188,
    0.625,
    0.0,
    0.9117876887321472,
    0.8726513385772705,
    0.8608964681625366,
    0.8839778900146484,
    0.6688033938407898,
    0.7851662635803223,
    0.8484042286872864,
    0.6005361676216125,
    0.0,
    0.7705956697463989,
    0.7092198729515076,
    0.6500955820083618,
    0.3333333432674408,
    0.4111675024032593,
    0.0,
    0.0555555559694767,
    0.9179056286811829,
    0.8362264037132263,
    0.8296507596969604,
    0.7888161540031433,
    0.800000011920929,
    0.8274399042129517,
    0.7810218930244446,
    0.7796102166175842,
    0.6070287823677063,
    0.0,
    0.6779089570045471,
    0.7885714173316956,
    0.6860465407371521,
    0.4451827108860016,
    0.5263158082962036,
    0.6124401688575745,
    0.0,
    0.23762376606464386,
    0.0,
    0.8743902444839478,
    0.8946759104728699,
    0.8124238848686218,
    0.6826424598693848,
    0.7448015213012695,
    0.622613787651062,
    0.815571129322052,
    0.7886676788330078,
    0.6078665256500244,
    0.6062846779823303,
    0.6258503198623657,
    0.0,
    0.7748815417289734,
    0.7785714268684387,
    0.7917174100875854,
    0.684385359287262,
    0.7946577668190002,
    0.8486789464950562,
    0.8667199015617371,
    0.8801916837692261,
    0.7773386240005493,
    0.4444444477558136,
    0.5632184147834778,
    0.0,
    0.8328410983085632,
    0.8947368264198303,
    0.7614285945892334,
    0.9028571248054504,
    0.8945147395133972,
    0.9246343970298767,
    0.8795811533927917,
    0.8600337505340576,
    0.8600770235061646,
    0.3636363744735718,
    0.843589723110199,
    0.8316251635551453,
    0.8020434379577637,
    0.7174677848815918,
    0.9251700639724731,
    0.7785844206809998,
    0.8236380219459534,
    0.8355664014816284,
    0.8584474921226501,
    0.8786610960960388,
    0.8967452049255371,
    0.794331967830658,
    0.8967683911323547,
    0.8421494364738464,
    0.8517956733703613,
    0.8713693022727966,
    0.0,
    0.7437899112701416,
    0.8922261595726013,
    0.7450670599937439,
    0.8677918314933777,
    0.8525754809379578,
    0.9188544154167175,
    0.8709972500801086,
    0.0,
    0.8924247622489929,
    0.946167528629303,
    0.8920187950134277,
    0.8041958212852478,
    0.9268755912780762,
    0.8631240129470825,
    0.757446825504303,
    0.8684863448143005,
    0.84624844789505,
    0.8961424231529236,
    0.84748774766922,
    0.9070929288864136,
    0.8908246159553528,
    0.8663829565048218,
    0.9066358208656311,
    0.9053373336791992,
    0.7016393542289734,
    0.8903061151504517,
    0.8892955183982849,
    0.8157303333282471,
    0.5854616761207581,
    0.0,
    0.8695651888847351,
    0.9057239294052124,
    0.8757319450378418,
    0.7311643958091736,
    0.8246445655822754,
    0.6978723406791687,
    0.3857142925262451,
    0.8153215050697327,
    0.8302114605903625,
    0.8675691485404968,
    0.8993218541145325,
    0.9194597005844116,
    0.8820512890815735,
    0.928699791431427,
    0.8148747086524963,
    0.8461538553237915,
    0.800431489944458,
    0.9095792174339294,
    0.863070547580719,
    0.8754076957702637,
    0.9154098629951477,
    0.8381317853927612,
    0.8697749376296997,
    0.8601190447807312,
    0.8023032546043396,
    0.9124270081520081,
    0.9438735246658325,
    0.8590412735939026,
    0.8188638687133789,
    0.8316831588745117,
    0.9024745225906372,
    0.8581560254096985,
    0.4304267168045044,
    0.0,
    0.7953929305076599,
    0.8390712738037109,
    0.8726061582565308,
    0.8405560255050659,
    0.752662718296051,
    0.43589743971824646,
    0.7582204937934875,
    0.05727923661470413,
    0.056603774428367615,
    0.6075061559677124,
    0.7860261797904968,
    0.8741007447242737,
    0.8981180787086487,
    0.7848275899887085,
    0.7554709911346436,
    0.621082603931427,
    0.7487073540687561,
    0.759856641292572,
    0.8298086524009705,
    0.790281355381012,
    0.6000000238418579,
    0.125,
    0.0,
    0.9047237634658813,
    0.8963445425033569,
    0.8823987245559692,
    0.9352697134017944,
    0.9356521964073181,
    0.935982346534729,
    0.8804243206977844,
    0.8406153917312622,
    0.8352344632148743,
    0.8135152459144592,
    0.775254487991333,
    0.7713717818260193,
    0.7733071446418762,
    0.7664835453033447,
    0.7088607549667358,
    0.25961539149284363,
    0.7746371030807495,
    0.8348701000213623,
    0.7002067565917969,
    0.8348689079284668,
    0.8598130941390991,
    0.7259474992752075,
    0.7468634843826294,
    0.8159564733505249,
    0.8059701323509216,
    0.770370364189148,
    0.6897746920585632,
    0.745920717716217,
    0.6733167171478271,
    0.447761207818985,
    0.0,
    0.0,
    0.7753797173500061,
    0.830314576625824,
    0.8182692527770996,
    0.7625145316123962,
    0.8298807144165039,
    0.8575146198272705,
    0.6141338348388672,
    0.6531073451042175,
    0.0,
    0.7864406704902649,
    0.523517370223999,
    0.8081002831459045,
    0.8392484188079834,
    0.8350253701210022,
    0.7980295419692993,
    0.6644518375396729,
    0.0,
    0.8544739484786987,
    0.7711442708969116,
    0.7014114856719971,
    0.7085370421409607,
    0.7319963574409485,
    0.7401685118675232,
    0.7793923616409302,
    0.7298049926757812,
    0.44251206517219543,
    0.532920241355896,
    0.4121280312538147,
    0.3346354067325592,
    0.22033898532390594,
    0.2188679277896881,
    0.7447795867919922,
    0.8156097531318665,
    0.8447937369346619,
    0.9031690359115601,
    0.9096446633338928,
    0.580152690410614,
    0.0,
    0.6970954537391663,
    0.7114093899726868,
    0.5738636255264282,
    0.37362638115882874,
    0.3601532578468323,
    0.095238097012043,
    0.0
  ],
  "mean_dice": 0.7024685144424438,
  "cache_manifest_sha256": "2f3878f9607be145f18aa0bcf3fc56e34c00c09a048af5fcb3a5e43b5ce5b6e4",
  "head_checkpoint_sha256": "d1db596006285cd3c07b63924c249d170ed2d22fe551773e5b9d59820f715d29",
  "training_elapsed_s": 30.75523281097412,
  "use_amp_bf16": true,
  "schema_version": "feat_cache_v1"
}