{
  "task": "acdc_lv",
  "fm": "efficientnet_b0",
  "seed": 45,
  "n_test": 361,
  "test_ids": [
    "patient003_frame01_slice000",
    "patient003_frame01_slice001",
    "patient003_frame01_slice002",
    "patient003_frame01_slice003",
    "patient003_frame01_slice004",
    "patient003_frame01_slice005",
    "patient003_frame01_slice006",
    "patient003_frame01_slice007",
    "patient003_frame01_slice008",
    "patient003_frame01_slice009",
    "patient003_frame15_slice000",
    "patient003_frame15_slice001",
    "patient003_frame15_slice002",
    "patient003_frame15_slice003",
    "patient003_frame15_slice004",
    "patient003_frame15_slice005",
    "patient003_frame15_slice006",
    "patient003_frame15_slice007",
    "patient003_frame15_slice008",
    "patient003_frame15_slice009",
    "patient005_frame01_slice000",
    "patient005_frame01_slice001",
    "patient005_frame01_slice002",
    "patient005_frame01_slice003",
    "patient005_frame01_slice004",
    "patient005_frame01_slice005",
    "patient005_frame01_slice006",
    "patient005_frame01_slice007",
    "patient005_frame01_slice008",
    "patient005_frame01_slice009",
    "patient005_frame13_slice000",
    "patient005_frame13_slice001",
    "patient005_frame13_slice002",
    "patient005_frame13_slice003",
    "patient005_frame13_slice004",
    "patient005_frame13_slice005",
    "patient005_frame13_slice006",
    "patient005_frame13_slice007",
    "patient005_frame13_slice008",
    "patient005_frame13_slice009",
    "patient019_frame01_slice000",
    "patient019_frame01_slice001",
    "patient019_frame01_slice002",
    "patient019_frame01_slice003",
    "patient019_frame01_slice004",
    "patient019_frame01_slice005",
    "patient019_frame01_slice006",
    "patient019_frame01_slice007",
    "patient019_frame01_slice008",
    "patient019_frame01_slice009",
    "patient019_frame01_slice010",
    "patient019_frame11_slice000",
    "patient019_frame11_slice001",
    "patient019_frame11_slice002",
    "patient019_frame11_slice003",
    "patient019_frame11_slice004",
    "patient019_frame11_slice005",
    "patient019_frame11_slice006",
    "patient019_frame11_slice007",
    "patient019_frame11_slice008",
    "patient019_frame11_slice009",
    "patient022_frame01_slice000",
    "patient022_frame01_slice001",
    "patient022_frame01_slice002",
    "patient022_frame01_slice003",
    "patient022_frame01_slice004",
    "patient022_frame01_slice005",
    "patient022_frame01_slice006",
    "patient022_frame11_slice000",
    "patient022_frame11_slice001",
    "patient022_frame11_slice002",
    "patient022_frame11_slice003",
    "patient022_frame11_slice004",
    "patient022_frame11_slice005",
    "patient022_frame11_slice006",
    "patient025_frame01_slice000",
    "patient025_frame01_slice001",
    "patient025_frame01_slice002",
    "patient025_frame01_slice003",
    "patient025_frame01_slice004",
    "patient025_frame01_slice005",
    "patient025_frame01_slice006",
    "patient025_frame01_slice007",
    "patient025_frame01_slice008",
    "patient025_frame09_slice000",
    "patient025_frame09_slice001",
    "patient025_frame09_slice002",
    "patient025_frame09_slice003",
    "patient025_frame09_slice004",
    "patient025_frame09_slice005",
    "patient025_frame09_slice006",
    "patient025_frame09_slice007",
    "patient025_frame09_slice008",
    "patient026_frame01_slice000",
    "patient026_frame01_slice001",
    "patient026_frame01_slice002",
    "patient026_frame01_slice003",
    "patient026_frame01_slice004",
    "patient026_frame01_slice005",
    "patient026_frame01_slice006",
    "patient026_frame01_slice007",
    "patient026_frame01_slice008",
    "patient026_frame01_slice009",
    "patient026_frame12_slice001",
    "patient026_frame12_slice002",
    "patient026_frame12_slice003",
    "patient026_frame12_slice004",
    "patient026_frame12_slice005",
    "patient026_frame12_slice006",
    "patient026_frame12_slice007",
    "patient026_frame12_slice008",
    "patient028_frame01_slice000",
    "patient028_frame01_slice001",
    "patient028_frame01_slice002",
    "patient028_frame01_slice003",
    "patient028_frame01_slice004",
    "patient028_frame01_slice005",
    "patient028_frame01_slice006",
    "patient028_frame01_slice007",
    "patient028_frame01_slice008",
    "patient028_frame09_slice000",
    "patient028_frame09_slice001",
    "patient028_frame09_slice002",
    "patient028_frame09_slice003",
    "patient028_frame09_slice004",
    "patient028_frame09_slice005",
    "patient028_frame09_slice006",
    "patient034_frame01_slice000",
    "patient034_frame01_slice001",
    "patient034_frame01_slice002",
    "patient034_frame01_slice003",
    "patient034_frame01_slice004",
    "patient034_frame01_slice005",
    "patient034_frame01_slice006",
    "patient034_frame01_slice007",
    "patient034_frame01_slice008",
    "patient034_frame01_slice009",
    "patient034_frame16_slice000",
    "patient034_frame16_slice001",
    "patient034_frame16_slice002",
    "patient034_frame16_slice003",
    "patient034_frame16_slice004",
    "patient034_frame16_slice005",
    "patient034_frame16_slice006",
    "patient034_frame16_slice007",
    "patient034_frame16_slice008",
    "patient043_frame01_slice000",
    "patient043_frame01_slice001",
    "patient043_frame01_slice002",
    "patient043_frame01_slice003",
    "patient043_frame01_slice004",
    "patient043_frame01_slice005",
    "patient043_frame01_slice006",
    "patient043_frame01_slice007",
    "patient043_frame01_slice008",
    "patient043_frame01_slice009",
    "patient043_frame01_slice010",
    "patient043_frame01_slice011",
    "patient043_frame07_slice000",
    "patient043_frame07_slice001",
    "patient043_frame07_slice002",
    "patient043_frame07_slice003",
    "patient043_frame07_slice004",
    "patient043_frame07_slice005",
    "patient043_frame07_slice006",
    "patient043_frame07_slice007",
    "patient043_frame07_slice008",
    "patient043_frame07_slice009",
    "patient043_frame07_slice010",
    "patient043_frame07_slice011",
    "patient051_frame01_slice000",
    "patient051_frame01_slice001",
    "patient051_frame01_slice002",
    "patient051_frame01_slice003",
    "patient051_frame01_slice004",
    "patient051_frame01_slice005",
    "patient051_frame01_slice006",
    "patient051_frame01_slice007",
    "patient051_frame01_slice008",
    "patient051_frame01_slice009",
    "patient051_frame11_slice001",
    "patient051_frame11_slice002",
    "patient051_frame11_slice003",
    "patient051_frame11_slice004",
    "patient051_frame11_slice005",
    "patient051_frame11_slice006",
    "patient051_frame11_slice007",
    "patient051_frame11_slice008",
    "patient051_frame11_slice009",
    "patient052_frame01_slice000",
    "patient052_frame01_slice001",
    "patient052_frame01_slice002",
    "patient052_frame01_slice003",
    "patient052_frame01_slice004",
    "patient052_frame01_slice005",
    "patient052_frame01_slice006",
    "patient052_frame01_slice007",
    "patient052_frame09_slice000",
    "patient052_frame09_slice001",
    "patient052_frame09_slice002",
    "patient052_frame09_slice003",
    "patient052_frame09_slice004",
    "patient052_frame09_slice005",
    "patient052_frame09_slice006",
    "patient052_frame09_slice007",
    "patient053_frame01_slice000",
    "patient053_frame01_slice001",
    "patient053_frame01_slice002",
    "patient053_frame01_slice003",
    "patient053_frame01_slice004",
    "patient053_frame01_slice005",
    "patient053_frame01_slice006",
    "patient053_frame12_slice000",
    "patient053_frame12_slice001",
    "patient053_frame12_slice002",
    "patient053_frame12_slice003",
    "patient053_frame12_slice004",
    "patient053_frame12_slice005",
    "patient053_frame12_slice006",
    "patient057_frame01_slice000",
    "patient057_frame01_slice001",
    "patient057_frame01_slice002",
    "patient057_frame01_slice003",
    "patient057_frame01_slice004",
    "patient057_frame01_slice005",
    "patient057_frame01_slice006",
    "patient057_frame01_slice007",
    "patient057_frame09_slice000",
    "patient057_frame09_slice001",
    "patient057_frame09_slice002",
    "patient057_frame09_slice003",
    "patient057_frame09_slice004",
    "patient057_frame09_slice005",
    "patient057_frame09_slice006",
    "patient060_frame01_slice000",
    "patient060_frame01_slice001",
    "patient060_frame01_slice002",
    "patient060_frame01_slice003",
    "patient060_frame01_slice004",
    "patient060_frame01_slice005",
    "patient060_frame01_slice006",
    "patient060_frame01_slice007",
    "patient060_frame01_slice008",
    "patient060_frame14_slice001",
    "patient060_frame14_slice002",
    "patient060_frame14_slice003",
    "patient060_frame14_slice004",
    "patient060_frame14_slice005",
    "patient060_frame14_slice006",
    "patient060_frame14_slice007",
    "patient060_frame14_slice008",
    "patient062_frame01_slice000",
    "patient062_frame01_slice001",
    "patient062_frame01_slice002",
    "patient062_frame01_slice003",
    "patient062_frame01_slice004",
    "patient062_frame01_slice005",
    "patient062_frame01_slice006",
    "patient062_frame01_slice007",
    "patient062_frame01_slice008",
    "patient062_frame01_slice009",
    "patient062_frame09_slice000",
    "patient062_frame09_slice001",
    "patient062_frame09_slice002",
    "patient062_frame09_slice003",
    "patient062_frame09_slice004",
    "patient062_frame09_slice005",
    "patient062_frame09_slice006",
    "patient062_frame09_slice007",
    "patient062_frame09_slice008",
    "patient072_frame01_slice000",
    "patient072_frame01_slice001",
    "patient072_frame01_slice002",
    "patient072_frame01_slice003",
    "patient072_frame01_slice004",
    "patient072_frame01_slice005",
    "patient072_frame01_slice006",
    "patient072_frame11_slice000",
    "patient072_frame11_slice001",
    "patient072_frame11_slice002",
    "patient072_frame11_slice003",
    "patient072_frame11_slice004",
    "patient072_frame11_slice005",
    "patient072_frame11_slice006",
    "patient082_frame01_slice000",
    "patient082_frame01_slice001",
    "patient082_frame01_slice002",
    "patient082_frame01_slice003",
    "patient082_frame01_slice004",
    "patient082_frame01_slice005",
    "patient082_frame01_slice006",
    "patient082_frame01_slice007",
    "patient082_frame01_slice008",
    "patient082_frame01_slice009",
    "patient082_frame01_slice010",
    "patient082_frame01_slice011",
    "patient082_frame01_slice012",
    "patient082_frame01_slice013",
    "patient082_frame01_slice014",
    "patient082_frame01_slice015",
    "patient082_frame07_slice000",
    "patient082_frame07_slice001",
    "patient082_frame07_slice002",
    "patient082_frame07_slice003",
    "patient082_frame07_slice004",
    "patient082_frame07_slice005",
    "patient082_frame07_slice006",
    "patient082_frame07_slice007",
    "patient082_frame07_slice008",
    "patient082_frame07_slice009",
    "patient082_frame07_slice010",
    "patient082_frame07_slice011",
    "patient082_frame07_slice012",
    "patient082_frame07_slice013",
    "patient082_frame07_slice014",
    "patient082_frame07_slice015",
    "patient093_frame01_slice000",
    "patient093_frame01_slice001",
    "patient093_frame01_slice002",
    "patient093_frame01_slice003",
    "patient093_frame01_slice004",
    "patient093_frame01_slice005",
    "patient093_frame01_slice006",
    "patient093_frame01_slice007",
    "patient093_frame01_slice008",
    "patient093_frame14_slice001",
    "patient093_frame14_slice002",
    "patient093_frame14_slice003",
    "patient093_frame14_slice004",
    "patient093_frame14_slice005",
    "patient093_frame14_slice006",
    "patient093_frame14_slice007",
    "patient093_frame14_slice008",
    "patient098_frame01_slice000",
    "patient098_frame01_slice001",
    "patient098_frame01_slice002",
    "patient098_frame01_slice003",
    "patient098_frame01_slice004",
    "patient098_frame01_slice005",
    "patient098_frame01_slice006",
    "patient098_frame09_slice000",
    "patient098_frame09_slice001",
    "patient098_frame09_slice002",
    "patient098_frame09_slice003",
    "patient098_frame09_slice004",
    "patient098_frame09_slice005",
    "patient098_frame09_slice006",
    "patient100_frame01_slice000",
    "patient100_frame01_slice001",
    "patient100_frame01_slice002",
    "patient100_frame01_slice003",
    "patient100_frame01_slice004",
    "patient100_frame01_slice005",
    "patient100_frame01_slice006",
    "patient100_frame13_slice000",
    "patient100_frame13_slice001",
    "patient100_frame13_slice002",
    "patient100_frame13_slice003",
    "patient100_frame13_slice004",
    "patient100_frame13_slice005",
    "patient100_frame13_slice006"
  ],
  "per_case_dice": [
    0.0,
    0.3090195953845978,
    0.6876364946365356,
    0.15094339847564697,
    0.09456869214773178,
    0.48912325501441956,
    0.26482805609703064,
    0.44147157669067383,
    0.518207311630249,
    0.0,
    0.0,
    0.21600770950317383,
    0.6659929156303406,
    0.36916235089302063,
    0.019174041226506233,
    0.5852348804473877,
    0.2569531798362732,
    0.5505836606025696,
    0.6616541147232056,
    0.0,
    0.7475345134735107,
    0.7704874873161316,
    0.7904717922210693,
    0.751857340335846,
    0.8586323261260986,
    0.36253443360328674,
    0.8253412842750549,
    0.6729857921600342,
    0.6824281215667725,
    0.197158083319664,
    0.0,
    0.8292268514633179,
    0.6478250026702881,
    0.7897526621818542,
    0.80361008644104,
    0.7258126139640808,
    0.6087194681167603,
    0.6058678030967712,
    0.740882933139801,
    0.48924732208251953,
    0.801483154296875,
    0.8335695862770081,
    0.9072638750076294,
    0.7694491744041443,
    0.7852794528007507,
    0.8739117980003357,
    0.7227599620819092,
    0.8965231776237488,
    0.0,
    0.1690140813589096,
    0.0,
    0.7201735377311707,
    0.8244755268096924,
    0.7858846187591553,
    0.10347174853086472,
    0.8663697242736816,
    0.8892045617103577,
    0.7954198718070984,
    0.3658088147640228,
    0.0,
    0.006896551698446274,
    0.7228739261627197,
    0.638568103313446,
    0.6313775777816772,
    0.1974789947271347,
    0.0,
    0.0,
    0.0,
    0.15677966177463531,
    0.21014492213726044,
    0.0,
    0.0,
    0.0,
    0.0,
    0.0,
    0.600468635559082,
    0.8301176428794861,
    0.816615104675293,
    0.32418951392173767,
    0.3066132366657257,
    0.0,
    0.6738949418067932,
    0.0,
    0.0,
    0.6098397970199585,
    0.6731391549110413,
    0.3534482717514038,
    0.0,
    0.0,
    0.0,
    0.0,
    0.0,
    0.0,
    0.567543625831604,
    0.7354409098625183,
    0.33848798274993896,
    0.26985350251197815,
    0.0,
    0.0,
    0.0,
    0.6337509155273438,
    0.0,
    0.0,
    0.5059602856636047,
    0.0,
    0.0,
    0.0,
    0.0,
    0.0,
    0.0,
    0.0,
    0.5333911776542664,
    0.49203264713287354,
    0.6076986193656921,
    0.14775726199150085,
    0.5679758191108704,
    0.0,
    0.0,
    0.0,
    0.0,
    0.30168068408966064,
    0.23426572978496552,
    0.4528301954269409,
    0.4253521263599396,
    0.0,
    0.0,
    0.0,
    0.754023015499115,
    0.16766467690467834,
    0.8214016556739807,
    0.5044510364532471,
    0.7211478352546692,
    0.6402714848518372,
    0.5879917144775391,
    0.5576679110527039,
    0.4149068295955658,
    0.0,
    0.11522633582353592,
    0.2685714364051819,
    0.0,
    0.0,
    0.05911330133676529,
    0.0,
    0.1418764293193817,
    0.0,
    0.0933062881231308,
    0.4517610967159271,
    0.566317081451416,
    0.230699360370636,
    0.19572953879833221,
    0.0,
    0.016913319006562233,
    0.0,
    0.3472222089767456,
    0.2849673330783844,
    0.0,
    0.0,
    0.0,
    0.14705882966518402,
    0.27299702167510986,
    0.0,
    0.10459183901548386,
    0.0,
    0.0,
    0.0,
    0.0,
    0.0,
    0.0,
    0.0,
    0.0,
    0.7623456716537476,
    0.5094509720802307,
    0.6632047295570374,
    0.7880539298057556,
    0.6155276894569397,
    0.6638432741165161,
    0.520510196685791,
    0.4819175899028778,
    0.4476110637187958,
    0.0,
    0.0,
    0.7747747898101807,
    0.7843137383460999,
    0.4571428596973419,
    0.43417084217071533,
    0.4721815586090088,
    0.48495733737945557,
    0.49776187539100647,
    0.1338289976119995,
    0.7127071619033813,
    0.6860465407371521,
    0.5990058183670044,
    0.7183170914649963,
    0.7166853547096252,
    0.5803893208503723,
    0.0,
    0.0,
    0.561529278755188,
    0.6539682745933533,
    0.48275861144065857,
    0.5452229380607605,
    0.0024449878837913275,
    0.24598930776119232,
    0.0,
    0.0,
    0.7661221027374268,
    0.8143157958984375,
    0.6951923370361328,
    0.8176513314247131,
    0.7292993664741516,
    0.6047700047492981,
    0.512922465801239,
    0.5360824465751648,
    0.04804045334458351,
    0.0,
    0.5251312851905823,
    0.7108874917030334,
    0.0,
    0.6373626589775085,
    0.7352456450462341,
    0.658963143825531,
    0.3270646035671234,
    0.1363128423690796,
    0.0,
    0.0,
    0.5018633604049683,
    0.0,
    0.5398660898208618,
    0.563425600528717,
    0.5698143839836121,
    0.0,
    0.0,
    0.0,
    0.32712215185165405,
    0.866869330406189,
    0.6645941138267517,
    0.8626799583435059,
    0.7457420825958252,
    0.8181818127632141,
    0.6255379915237427,
    0.7886266112327576,
    0.5644329786300659,
    0.0,
    0.5633017420768738,
    0.7830017805099487,
    0.8460891246795654,
    0.6051453948020935,
    0.5261083841323853,
    0.7334710955619812,
    0.794460654258728,
    0.0,
    0.47631755471229553,
    0.5116279125213623,
    0.7831206917762756,
    0.7480000257492065,
    0.3130287528038025,
    0.7517188787460327,
    0.7943859696388245,
    0.0,
    0.0,
    0.0,
    0.0,
    0.0,
    0.24707846343517303,
    0.0,
    0.0117647061124444,
    0.0,
    0.14977973699569702,
    0.0,
    0.0,
    0.6651198863983154,
    0.8444976210594177,
    0.11201866716146469,
    0.8803418874740601,
    0.765753448009491,
    0.5265251994132996,
    0.5401929020881653,
    0.5874799489974976,
    0.6029654145240784,
    0.7945516705513,
    0.1927083283662796,
    0.48076921701431274,
    0.18025077879428864,
    0.0,
    0.6491107940673828,
    0.6663376092910767,
    0.6225303411483765,
    0.7239819169044495,
    0.5701754093170166,
    0.82163405418396,
    0.7454357743263245,
    0.8307692408561707,
    0.7789605259895325,
    0.6417403221130371,
    0.5891696810722351,
    0.34293192625045776,
    0.579200029373169,
    0.0,
    0.0,
    0.0,
    0.32928311824798584,
    0.20378457009792328,
    0.5824238657951355,
    0.6444708704948425,
    0.6469719409942627,
    0.5064733028411865,
    0.6426540017127991,
    0.5912334322929382,
    0.28014183044433594,
    0.0,
    0.0,
    0.0,
    0.0,
    0.0,
    0.0,
    0.0,
    0.20588235557079315,
    0.7209492921829224,
    0.6554675102233887,
    0.4843893349170685,
    0.6011521220207214,
    0.7311320900917053,
    0.5921052694320679,
    0.5797788500785828,
    0.1387755125761032,
    0.6247190833091736,
    0.0,
    0.6591675877571106,
    0.6710963249206543,
    0.0,
    0.0,
    0.018099548295140266,
    0.0258397925645113,
    0.47018739581108093,
    0.6399324536323547,
    0.45393258333206177,
    0.0,
    0.014285714365541935,
    0.7703056931495667,
    0.31216931343078613,
    0.0,
    0.4750642776489258,
    0.31221720576286316,
    0.04282655194401741,
    0.37889689207077026,
    0.0,
    0.08123249560594559,
    0.0,
    0.0,
    0.034246575087308884,
    0.6517133712768555,
    0.7879418134689331,
    0.0,
    0.7616580128669739,
    0.0,
    0.0,
    0.0,
    0.0,
    0.0,
    0.0,
    0.0
  ],
  "mean_dice": 0.36207833886146545,
  "cache_manifest_sha256": "e0a6b5c3a4c7643f99bce4d8765760257c69ea127a9427a24ee8456605a34b41",
  "head_checkpoint_sha256": "580e2ca95484610280e01be218c25723ddd667d51a1a6dac4a7cea0aa1437a9c",
  "training_elapsed_s": 18.96361231803894,
  "use_amp_bf16": true,
  "schema_version": "feat_cache_v1"
}