{
  "task": "riga_disc",
  "fm": "deit_vitb16",
  "seed": 44,
  "n_test": 95,
  "test_ids": [
    "Magrabia/MagrabiFemale/image1.tif",
    "Magrabia/MagrabiFemale/image10.tif",
    "Magrabia/MagrabiFemale/image11.tif",
    "Magrabia/MagrabiFemale/image12.tif",
    "Magrabia/MagrabiFemale/image14.tif",
    "Magrabia/MagrabiFemale/image15.tif",
    "Magrabia/MagrabiFemale/image16.tif",
    "Magrabia/MagrabiFemale/image17.tif",
    "Magrabia/MagrabiFemale/image19.tif",
    "Magrabia/MagrabiFemale/image2.tif",
    "Magrabia/MagrabiFemale/image20.tif",
    "Magrabia/MagrabiFemale/image22.tif",
    "Magrabia/MagrabiFemale/image23.tif",
    "Magrabia/MagrabiFemale/image24.tif",
    "Magrabia/MagrabiFemale/image25.tif",
    "Magrabia/MagrabiFemale/image26.tif",
    "Magrabia/MagrabiFemale/image27.tif",
    "Magrabia/MagrabiFemale/image29.tif",
    "Magrabia/MagrabiFemale/image3.tif",
    "Magrabia/MagrabiFemale/image30.tif",
    "Magrabia/MagrabiFemale/image31.tif",
    "Magrabia/MagrabiFemale/image33.tif",
    "Magrabia/MagrabiFemale/image34.tif",
    "Magrabia/MagrabiFemale/image35.tif",
    "Magrabia/MagrabiFemale/image36.tif",
    "Magrabia/MagrabiFemale/image37.tif",
    "Magrabia/MagrabiFemale/image38.tif",
    "Magrabia/MagrabiFemale/image39.tif",
    "Magrabia/MagrabiFemale/image40.tif",
    "Magrabia/MagrabiFemale/image41.tif",
    "Magrabia/MagrabiFemale/image42.tif",
    "Magrabia/MagrabiFemale/image44.tif",
    "Magrabia/MagrabiFemale/image47.tif",
    "Magrabia/MagrabiFemale/image48.tif",
    "Magrabia/MagrabiFemale/image5.tif",
    "Magrabia/MagrabiFemale/image6.tif",
    "Magrabia/MagrabiFemale/image7.tif",
    "Magrabia/MagrabiFemale/image9.tif",
    "Magrabia/MagrabiaMale/image1.tif",
    "Magrabia/MagrabiaMale/image12.tif",
    "Magrabia/MagrabiaMale/image14.tif",
    "Magrabia/MagrabiaMale/image15.tif",
    "Magrabia/MagrabiaMale/image16.tif",
    "Magrabia/MagrabiaMale/image17.tif",
    "Magrabia/MagrabiaMale/image18.tif",
    "Magrabia/MagrabiaMale/image2.tif",
    "Magrabia/MagrabiaMale/image20.tif",
    "Magrabia/MagrabiaMale/image21.tif",
    "Magrabia/MagrabiaMale/image24.tif",
    "Magrabia/MagrabiaMale/image25.tif",
    "Magrabia/MagrabiaMale/image26.tif",
    "Magrabia/MagrabiaMale/image28.tif",
    "Magrabia/MagrabiaMale/image29.tif",
    "Magrabia/MagrabiaMale/image3.tif",
    "Magrabia/MagrabiaMale/image30.tif",
    "Magrabia/MagrabiaMale/image31.tif",
    "Magrabia/MagrabiaMale/image32.tif",
    "Magrabia/MagrabiaMale/image33.tif",
    "Magrabia/MagrabiaMale/image35.tif",
    "Magrabia/MagrabiaMale/image36.tif",
    "Magrabia/MagrabiaMale/image37.tif",
    "Magrabia/MagrabiaMale/image38.tif",
    "Magrabia/MagrabiaMale/image39.tif",
    "Magrabia/MagrabiaMale/image4.tif",
    "Magrabia/MagrabiaMale/image40.tif",
    "Magrabia/MagrabiaMale/image41.tif",
    "Magrabia/MagrabiaMale/image42.tif",
    "Magrabia/MagrabiaMale/image43.tif",
    "Magrabia/MagrabiaMale/image44.tif",
    "Magrabia/MagrabiaMale/image45.tif",
    "Magrabia/MagrabiaMale/image47.tif",
    "Magrabia/MagrabiaMale/image5.tif",
    "Magrabia/MagrabiaMale/image6.tif",
    "Magrabia/MagrabiaMale/image7.tif",
    "Magrabia/MagrabiaMale/image8.tif",
    "Magrabia/MagrabiaMale/image9.tif",
    "Magrabia/MagrabiFemale/image13.tif",
    "Magrabia/MagrabiFemale/image18.tif",
    "Magrabia/MagrabiFemale/image21.tif",
    "Magrabia/MagrabiFemale/image28.tif",
    "Magrabia/MagrabiFemale/image32.tif",
    "Magrabia/MagrabiFemale/image4.tif",
    "Magrabia/MagrabiFemale/image43.tif",
    "Magrabia/MagrabiFemale/image45.tif",
    "Magrabia/MagrabiFemale/image46.tif",
    "Magrabia/MagrabiFemale/image8.tif",
    "Magrabia/MagrabiaMale/image10.tif",
    "Magrabia/MagrabiaMale/image11.tif",
    "Magrabia/MagrabiaMale/image13.tif",
    "Magrabia/MagrabiaMale/image19.tif",
    "Magrabia/MagrabiaMale/image22.tif",
    "Magrabia/MagrabiaMale/image23.tif",
    "Magrabia/MagrabiaMale/image27.tif",
    "Magrabia/MagrabiaMale/image34.tif",
    "Magrabia/MagrabiaMale/image46.tif"
  ],
  "per_case_dice": [
    0.9312937259674072,
    0.9269720911979675,
    0.925083339214325,
    0.83073890209198,
    0.955244779586792,
    0.8827999830245972,
    0.9112566709518433,
    0.9153905510902405,
    0.9110138416290283,
    0.9192151427268982,
    0.8920257091522217,
    0.9203388094902039,
    0.9184118509292603,
    0.9592360258102417,
    0.9207853674888611,
    0.9186934232711792,
    0.8974086046218872,
    0.9047756791114807,
    0.902665376663208,
    0.943664014339447,
    0.9498259425163269,
    0.9200410842895508,
    0.9534181356430054,
    0.9125069975852966,
    0.8586052656173706,
    0.8814828395843506,
    0.709441602230072,
    0.9400873184204102,
    0.9066262245178223,
    0.9224446415901184,
    0.9218968152999878,
    0.9406060576438904,
    0.9627923965454102,
    0.8068880438804626,
    0.9431236982345581,
    0.7876704931259155,
    0.8728505969047546,
    0.8569028377532959,
    0.7114062905311584,
    0.9106847643852234,
    0.8661462068557739,
    0.8937288522720337,
    0.8259180784225464,
    0.930008053779602,
    0.9053654670715332,
    0.8590242266654968,
    0.902236819267273,
    0.8822471499443054,
    0.9231735467910767,
    0.9056735038757324,
    0.8689124584197998,
    0.8762229084968567,
    0.9356767535209656,
    0.923270046710968,
    0.9377723336219788,
    0.8546414971351624,
    0.8840152025222778,
    0.8775067925453186,
    0.9325706958770752,
    0.9357618689537048,
    0.9023705720901489,
    0.9474560022354126,
    0.9527458548545837,
    0.9070971012115479,
    0.9074829816818237,
    0.9317998290061951,
    0.9589002132415771,
    0.9428743124008179,
    0.9090113639831543,
    0.9465846419334412,
    0.9202749133110046,
    0.9143872857093811,
    0.9564192891120911,
    0.8983684182167053,
    0.9053025841712952,
    0.9257545471191406,
    0.8616890907287598,
    0.951317548751831,
    0.942744255065918,
    0.8684613108634949,
    0.8680702447891235,
    0.9383945465087891,
    0.9309526085853577,
    0.8847833275794983,
    0.9130801558494568,
    0.8904109597206116,
    0.8956121206283569,
    0.9337327480316162,
    0.95716392993927,
    0.9379464983940125,
    0.8647786378860474,
    0.9100861549377441,
    0.8593109250068665,
    0.9461332559585571,
    0.9390280842781067
  ],
  "mean_dice": 0.9052285552024841,
  "cache_manifest_sha256": "366bb0f87ff8d928983a1c2fad0821727d013699d7642c09ea7678c03c92cf7e",
  "head_checkpoint_sha256": "bdc9f76d4deb867a3dbad83bb4d7e87047e8dbe5e6a205cb20cfb7cef8d4eff9",
  "training_elapsed_s": 8.826547384262085,
  "use_amp_bf16": true,
  "schema_version": "feat_cache_v1"
}