{
  "task": "acdc_lv",
  "fm": "resnet50",
  "seed": 43,
  "n_test": 361,
  "test_ids": [
    "patient003_frame01_slice000",
    "patient003_frame01_slice001",
    "patient003_frame01_slice002",
    "patient003_frame01_slice003",
    "patient003_frame01_slice004",
    "patient003_frame01_slice005",
    "patient003_frame01_slice006",
    "patient003_frame01_slice007",
    "patient003_frame01_slice008",
    "patient003_frame01_slice009",
    "patient003_frame15_slice000",
    "patient003_frame15_slice001",
    "patient003_frame15_slice002",
    "patient003_frame15_slice003",
    "patient003_frame15_slice004",
    "patient003_frame15_slice005",
    "patient003_frame15_slice006",
    "patient003_frame15_slice007",
    "patient003_frame15_slice008",
    "patient003_frame15_slice009",
    "patient005_frame01_slice000",
    "patient005_frame01_slice001",
    "patient005_frame01_slice002",
    "patient005_frame01_slice003",
    "patient005_frame01_slice004",
    "patient005_frame01_slice005",
    "patient005_frame01_slice006",
    "patient005_frame01_slice007",
    "patient005_frame01_slice008",
    "patient005_frame01_slice009",
    "patient005_frame13_slice000",
    "patient005_frame13_slice001",
    "patient005_frame13_slice002",
    "patient005_frame13_slice003",
    "patient005_frame13_slice004",
    "patient005_frame13_slice005",
    "patient005_frame13_slice006",
    "patient005_frame13_slice007",
    "patient005_frame13_slice008",
    "patient005_frame13_slice009",
    "patient019_frame01_slice000",
    "patient019_frame01_slice001",
    "patient019_frame01_slice002",
    "patient019_frame01_slice003",
    "patient019_frame01_slice004",
    "patient019_frame01_slice005",
    "patient019_frame01_slice006",
    "patient019_frame01_slice007",
    "patient019_frame01_slice008",
    "patient019_frame01_slice009",
    "patient019_frame01_slice010",
    "patient019_frame11_slice000",
    "patient019_frame11_slice001",
    "patient019_frame11_slice002",
    "patient019_frame11_slice003",
    "patient019_frame11_slice004",
    "patient019_frame11_slice005",
    "patient019_frame11_slice006",
    "patient019_frame11_slice007",
    "patient019_frame11_slice008",
    "patient019_frame11_slice009",
    "patient022_frame01_slice000",
    "patient022_frame01_slice001",
    "patient022_frame01_slice002",
    "patient022_frame01_slice003",
    "patient022_frame01_slice004",
    "patient022_frame01_slice005",
    "patient022_frame01_slice006",
    "patient022_frame11_slice000",
    "patient022_frame11_slice001",
    "patient022_frame11_slice002",
    "patient022_frame11_slice003",
    "patient022_frame11_slice004",
    "patient022_frame11_slice005",
    "patient022_frame11_slice006",
    "patient025_frame01_slice000",
    "patient025_frame01_slice001",
    "patient025_frame01_slice002",
    "patient025_frame01_slice003",
    "patient025_frame01_slice004",
    "patient025_frame01_slice005",
    "patient025_frame01_slice006",
    "patient025_frame01_slice007",
    "patient025_frame01_slice008",
    "patient025_frame09_slice000",
    "patient025_frame09_slice001",
    "patient025_frame09_slice002",
    "patient025_frame09_slice003",
    "patient025_frame09_slice004",
    "patient025_frame09_slice005",
    "patient025_frame09_slice006",
    "patient025_frame09_slice007",
    "patient025_frame09_slice008",
    "patient026_frame01_slice000",
    "patient026_frame01_slice001",
    "patient026_frame01_slice002",
    "patient026_frame01_slice003",
    "patient026_frame01_slice004",
    "patient026_frame01_slice005",
    "patient026_frame01_slice006",
    "patient026_frame01_slice007",
    "patient026_frame01_slice008",
    "patient026_frame01_slice009",
    "patient026_frame12_slice001",
    "patient026_frame12_slice002",
    "patient026_frame12_slice003",
    "patient026_frame12_slice004",
    "patient026_frame12_slice005",
    "patient026_frame12_slice006",
    "patient026_frame12_slice007",
    "patient026_frame12_slice008",
    "patient028_frame01_slice000",
    "patient028_frame01_slice001",
    "patient028_frame01_slice002",
    "patient028_frame01_slice003",
    "patient028_frame01_slice004",
    "patient028_frame01_slice005",
    "patient028_frame01_slice006",
    "patient028_frame01_slice007",
    "patient028_frame01_slice008",
    "patient028_frame09_slice000",
    "patient028_frame09_slice001",
    "patient028_frame09_slice002",
    "patient028_frame09_slice003",
    "patient028_frame09_slice004",
    "patient028_frame09_slice005",
    "patient028_frame09_slice006",
    "patient034_frame01_slice000",
    "patient034_frame01_slice001",
    "patient034_frame01_slice002",
    "patient034_frame01_slice003",
    "patient034_frame01_slice004",
    "patient034_frame01_slice005",
    "patient034_frame01_slice006",
    "patient034_frame01_slice007",
    "patient034_frame01_slice008",
    "patient034_frame01_slice009",
    "patient034_frame16_slice000",
    "patient034_frame16_slice001",
    "patient034_frame16_slice002",
    "patient034_frame16_slice003",
    "patient034_frame16_slice004",
    "patient034_frame16_slice005",
    "patient034_frame16_slice006",
    "patient034_frame16_slice007",
    "patient034_frame16_slice008",
    "patient043_frame01_slice000",
    "patient043_frame01_slice001",
    "patient043_frame01_slice002",
    "patient043_frame01_slice003",
    "patient043_frame01_slice004",
    "patient043_frame01_slice005",
    "patient043_frame01_slice006",
    "patient043_frame01_slice007",
    "patient043_frame01_slice008",
    "patient043_frame01_slice009",
    "patient043_frame01_slice010",
    "patient043_frame01_slice011",
    "patient043_frame07_slice000",
    "patient043_frame07_slice001",
    "patient043_frame07_slice002",
    "patient043_frame07_slice003",
    "patient043_frame07_slice004",
    "patient043_frame07_slice005",
    "patient043_frame07_slice006",
    "patient043_frame07_slice007",
    "patient043_frame07_slice008",
    "patient043_frame07_slice009",
    "patient043_frame07_slice010",
    "patient043_frame07_slice011",
    "patient051_frame01_slice000",
    "patient051_frame01_slice001",
    "patient051_frame01_slice002",
    "patient051_frame01_slice003",
    "patient051_frame01_slice004",
    "patient051_frame01_slice005",
    "patient051_frame01_slice006",
    "patient051_frame01_slice007",
    "patient051_frame01_slice008",
    "patient051_frame01_slice009",
    "patient051_frame11_slice001",
    "patient051_frame11_slice002",
    "patient051_frame11_slice003",
    "patient051_frame11_slice004",
    "patient051_frame11_slice005",
    "patient051_frame11_slice006",
    "patient051_frame11_slice007",
    "patient051_frame11_slice008",
    "patient051_frame11_slice009",
    "patient052_frame01_slice000",
    "patient052_frame01_slice001",
    "patient052_frame01_slice002",
    "patient052_frame01_slice003",
    "patient052_frame01_slice004",
    "patient052_frame01_slice005",
    "patient052_frame01_slice006",
    "patient052_frame01_slice007",
    "patient052_frame09_slice000",
    "patient052_frame09_slice001",
    "patient052_frame09_slice002",
    "patient052_frame09_slice003",
    "patient052_frame09_slice004",
    "patient052_frame09_slice005",
    "patient052_frame09_slice006",
    "patient052_frame09_slice007",
    "patient053_frame01_slice000",
    "patient053_frame01_slice001",
    "patient053_frame01_slice002",
    "patient053_frame01_slice003",
    "patient053_frame01_slice004",
    "patient053_frame01_slice005",
    "patient053_frame01_slice006",
    "patient053_frame12_slice000",
    "patient053_frame12_slice001",
    "patient053_frame12_slice002",
    "patient053_frame12_slice003",
    "patient053_frame12_slice004",
    "patient053_frame12_slice005",
    "patient053_frame12_slice006",
    "patient057_frame01_slice000",
    "patient057_frame01_slice001",
    "patient057_frame01_slice002",
    "patient057_frame01_slice003",
    "patient057_frame01_slice004",
    "patient057_frame01_slice005",
    "patient057_frame01_slice006",
    "patient057_frame01_slice007",
    "patient057_frame09_slice000",
    "patient057_frame09_slice001",
    "patient057_frame09_slice002",
    "patient057_frame09_slice003",
    "patient057_frame09_slice004",
    "patient057_frame09_slice005",
    "patient057_frame09_slice006",
    "patient060_frame01_slice000",
    "patient060_frame01_slice001",
    "patient060_frame01_slice002",
    "patient060_frame01_slice003",
    "patient060_frame01_slice004",
    "patient060_frame01_slice005",
    "patient060_frame01_slice006",
    "patient060_frame01_slice007",
    "patient060_frame01_slice008",
    "patient060_frame14_slice001",
    "patient060_frame14_slice002",
    "patient060_frame14_slice003",
    "patient060_frame14_slice004",
    "patient060_frame14_slice005",
    "patient060_frame14_slice006",
    "patient060_frame14_slice007",
    "patient060_frame14_slice008",
    "patient062_frame01_slice000",
    "patient062_frame01_slice001",
    "patient062_frame01_slice002",
    "patient062_frame01_slice003",
    "patient062_frame01_slice004",
    "patient062_frame01_slice005",
    "patient062_frame01_slice006",
    "patient062_frame01_slice007",
    "patient062_frame01_slice008",
    "patient062_frame01_slice009",
    "patient062_frame09_slice000",
    "patient062_frame09_slice001",
    "patient062_frame09_slice002",
    "patient062_frame09_slice003",
    "patient062_frame09_slice004",
    "patient062_frame09_slice005",
    "patient062_frame09_slice006",
    "patient062_frame09_slice007",
    "patient062_frame09_slice008",
    "patient072_frame01_slice000",
    "patient072_frame01_slice001",
    "patient072_frame01_slice002",
    "patient072_frame01_slice003",
    "patient072_frame01_slice004",
    "patient072_frame01_slice005",
    "patient072_frame01_slice006",
    "patient072_frame11_slice000",
    "patient072_frame11_slice001",
    "patient072_frame11_slice002",
    "patient072_frame11_slice003",
    "patient072_frame11_slice004",
    "patient072_frame11_slice005",
    "patient072_frame11_slice006",
    "patient082_frame01_slice000",
    "patient082_frame01_slice001",
    "patient082_frame01_slice002",
    "patient082_frame01_slice003",
    "patient082_frame01_slice004",
    "patient082_frame01_slice005",
    "patient082_frame01_slice006",
    "patient082_frame01_slice007",
    "patient082_frame01_slice008",
    "patient082_frame01_slice009",
    "patient082_frame01_slice010",
    "patient082_frame01_slice011",
    "patient082_frame01_slice012",
    "patient082_frame01_slice013",
    "patient082_frame01_slice014",
    "patient082_frame01_slice015",
    "patient082_frame07_slice000",
    "patient082_frame07_slice001",
    "patient082_frame07_slice002",
    "patient082_frame07_slice003",
    "patient082_frame07_slice004",
    "patient082_frame07_slice005",
    "patient082_frame07_slice006",
    "patient082_frame07_slice007",
    "patient082_frame07_slice008",
    "patient082_frame07_slice009",
    "patient082_frame07_slice010",
    "patient082_frame07_slice011",
    "patient082_frame07_slice012",
    "patient082_frame07_slice013",
    "patient082_frame07_slice014",
    "patient082_frame07_slice015",
    "patient093_frame01_slice000",
    "patient093_frame01_slice001",
    "patient093_frame01_slice002",
    "patient093_frame01_slice003",
    "patient093_frame01_slice004",
    "patient093_frame01_slice005",
    "patient093_frame01_slice006",
    "patient093_frame01_slice007",
    "patient093_frame01_slice008",
    "patient093_frame14_slice001",
    "patient093_frame14_slice002",
    "patient093_frame14_slice003",
    "patient093_frame14_slice004",
    "patient093_frame14_slice005",
    "patient093_frame14_slice006",
    "patient093_frame14_slice007",
    "patient093_frame14_slice008",
    "patient098_frame01_slice000",
    "patient098_frame01_slice001",
    "patient098_frame01_slice002",
    "patient098_frame01_slice003",
    "patient098_frame01_slice004",
    "patient098_frame01_slice005",
    "patient098_frame01_slice006",
    "patient098_frame09_slice000",
    "patient098_frame09_slice001",
    "patient098_frame09_slice002",
    "patient098_frame09_slice003",
    "patient098_frame09_slice004",
    "patient098_frame09_slice005",
    "patient098_frame09_slice006",
    "patient100_frame01_slice000",
    "patient100_frame01_slice001",
    "patient100_frame01_slice002",
    "patient100_frame01_slice003",
    "patient100_frame01_slice004",
    "patient100_frame01_slice005",
    "patient100_frame01_slice006",
    "patient100_frame13_slice000",
    "patient100_frame13_slice001",
    "patient100_frame13_slice002",
    "patient100_frame13_slice003",
    "patient100_frame13_slice004",
    "patient100_frame13_slice005",
    "patient100_frame13_slice006"
  ],
  "per_case_dice": [
    0.17351597547531128,
    0.7511472105979919,
    0.7088455557823181,
    0.6306666731834412,
    0.762417197227478,
    0.6599353551864624,
    0.7280334830284119,
    0.0,
    0.43470484018325806,
    0.0,
    0.4438818693161011,
    0.6784343719482422,
    0.6799450516700745,
    0.7623188495635986,
    0.7005887031555176,
    0.7634782791137695,
    0.6871609687805176,
    0.0,
    0.45574772357940674,
    0.0,
    0.2526315748691559,
    0.7844066619873047,
    0.7612031698226929,
    0.8342635035514832,
    0.7800518870353699,
    0.8419475555419922,
    0.6817248463630676,
    0.7581459283828735,
    0.6971677541732788,
    0.29230770468711853,
    0.00997150968760252,
    0.6559766530990601,
    0.6330451369285583,
    0.8716289401054382,
    0.7830101847648621,
    0.642615556716919,
    0.8448448181152344,
    0.8294573426246643,
    0.871074378490448,
    0.16363635659217834,
    0.8077641129493713,
    0.691347599029541,
    0.7228608131408691,
    0.7869058847427368,
    0.5892781615257263,
    0.7920910716056824,
    0.7577937841415405,
    0.5643296241760254,
    0.5215960741043091,
    0.427293062210083,
    0.0,
    0.6808672547340393,
    0.8411681056022644,
    0.7185800075531006,
    0.17191600799560547,
    0.4159131944179535,
    0.8525363802909851,
    0.7736358642578125,
    0.4750271439552307,
    0.488752543926239,
    0.2802344262599945,
    0.7586820721626282,
    0.5245579481124878,
    0.5789990425109863,
    0.33365291357040405,
    0.1463414579629898,
    0.0,
    0.0,
    0.3029197156429291,
    0.5427682995796204,
    0.2693602740764618,
    0.03177405148744583,
    0.01698513887822628,
    0.0,
    0.0,
    0.6812373995780945,
    0.5511921644210815,
    0.6330196857452393,
    0.6869391798973083,
    0.591304361820221,
    0.38803088665008545,
    0.5431619882583618,
    0.3897280991077423,
    0.14399999380111694,
    0.39609333872795105,
    0.5322338938713074,
    0.0,
    0.0,
    0.20588235557079315,
    0.11602210253477097,
    0.0,
    0.07792207598686218,
    0.03575547784566879,
    0.552949070930481,
    0.005940594244748354,
    0.3005272448062897,
    0.6429468393325806,
    0.35274815559387207,
    0.36425724625587463,
    0.5502183437347412,
    0.0,
    0.0,
    0.0,
    0.0,
    0.5754656195640564,
    0.5498154759407043,
    0.0,
    0.0,
    0.0,
    0.0,
    0.0,
    0.5861806869506836,
    0.3114035129547119,
    0.4025973975658417,
    0.2857142984867096,
    0.5369774699211121,
    0.0,
    0.0,
    0.0,
    0.0,
    0.5334420800209045,
    0.2548672556877136,
    0.3140000104904175,
    0.0,
    0.0,
    0.0,
    0.0,
    0.8164116740226746,
    0.4693877696990967,
    0.6432276368141174,
    0.5678180456161499,
    0.57230144739151,
    0.49762067198753357,
    0.5183608531951904,
    0.4557377099990845,
    0.45879119634628296,
    0.07471264153718948,
    0.49013158679008484,
    0.4761904776096344,
    0.6505376100540161,
    0.2222222238779068,
    0.25421133637428284,
    0.08230452984571457,
    0.045554738491773605,
    0.1468254029750824,
    0.09850107133388519,
    0.7042253613471985,
    0.6603854298591614,
    0.6793368458747864,
    0.6395184397697449,
    0.32935917377471924,
    0.4424203038215637,
    0.41487279534339905,
    0.42292171716690063,
    0.22314049303531647,
    0.4326923191547394,
    0.0,
    0.0,
    0.6470588445663452,
    0.5304877758026123,
    0.4675527811050415,
    0.45554035902023315,
    0.3573243021965027,
    0.2772611975669861,
    0.2163742631673813,
    0.17041419446468353,
    0.3194444477558136,
    0.04278074949979782,
    0.0,
    0.0,
    0.7964004278182983,
    0.7804877758026123,
    0.8055281639099121,
    0.7494714856147766,
    0.502639889717102,
    0.5606257915496826,
    0.556199312210083,
    0.46064141392707825,
    0.1822916716337204,
    0.02218114584684372,
    0.25492382049560547,
    0.3517272174358368,
    0.4574616551399231,
    0.2816353142261505,
    0.38568830490112305,
    0.46279069781303406,
    0.0,
    0.6198473572731018,
    0.16946308314800262,
    0.7101531624794006,
    0.7269737124443054,
    0.6904512047767639,
    0.6723060011863708,
    0.4611172080039978,
    0.30129870772361755,
    0.8179551362991333,
    0.0,
    0.6878452897071838,
    0.5859284996986389,
    0.7516524791717529,
    0.5095277428627014,
    0.0024449878837913275,
    0.31631630659103394,
    0.22410866618156433,
    0.0,
    0.7465831637382507,
    0.64091956615448,
    0.7428571581840515,
    0.8248772621154785,
    0.4656488597393036,
    0.5986478328704834,
    0.5296609997749329,
    0.5173547863960266,
    0.5452898740768433,
    0.724252462387085,
    0.6232073307037354,
    0.4651162922382355,
    0.5205267071723938,
    0.6807228922843933,
    0.8033201098442078,
    0.3476898968219757,
    0.43697479367256165,
    0.7211155295372009,
    0.6623906493186951,
    0.7320125102996826,
    0.47101449966430664,
    0.0,
    0.6131687164306641,
    0.2587064802646637,
    0.7037037014961243,
    0.7455752491950989,
    0.0,
    0.2841981053352356,
    0.2182227224111557,
    0.6243752241134644,
    0.6285527348518372,
    0.7066766619682312,
    0.5883734822273254,
    0.6278248429298401,
    0.5879567265510559,
    0.8072429895401001,
    0.6653266549110413,
    0.0,
    0.5534246563911438,
    0.6737089157104492,
    0.7351283431053162,
    0.6465927362442017,
    0.6274694204330444,
    0.7782691121101379,
    0.720098614692688,
    0.0,
    0.662028968334198,
    0.543268084526062,
    0.8150234818458557,
    0.8015296459197998,
    0.9048067927360535,
    0.6502463221549988,
    0.5206477642059326,
    0.46405228972435,
    0.5816216468811035,
    0.0,
    0.5149028301239014,
    0.41382017731666565,
    0.6696428656578064,
    0.7746797204017639,
    0.2842639684677124,
    0.0,
    0.0,
    0.0,
    0.0,
    0.8047891855239868,
    0.7221643924713135,
    0.7301136255264282,
    0.8172042965888977,
    0.5917836427688599,
    0.6465798020362854,
    0.4282907545566559,
    0.4910714328289032,
    0.8804733753204346,
    0.5258774757385254,
    0.5379844903945923,
    0.3563579320907593,
    0.4665314257144928,
    0.07934336364269257,
    0.7728692293167114,
    0.5566097497940063,
    0.6957001090049744,
    0.7881448864936829,
    0.7860037088394165,
    0.7472104430198669,
    0.770348846912384,
    0.7099056839942932,
    0.6711129546165466,
    0.6458498239517212,
    0.5687474608421326,
    0.5276225805282593,
    0.13812154531478882,
    0.3174603283405304,
    0.24121405184268951,
    0.0,
    0.0,
    0.17469879984855652,
    0.4800964891910553,
    0.6064049601554871,
    0.5075047016143799,
    0.5659090876579285,
    0.5632563233375549,
    0.4888888895511627,
    0.40874525904655457,
    0.5895734429359436,
    0.3763837516307831,
    0.21934501826763153,
    0.0997067466378212,
    0.0,
    0.0,
    0.0,
    0.7552346587181091,
    0.0,
    0.0,
    0.8265124559402466,
    0.6427238583564758,
    0.5200340747833252,
    0.0,
    0.5460751056671143,
    0.0,
    0.3915271461009979,
    0.7786885499954224,
    0.468265175819397,
    0.4467483460903168,
    0.0,
    0.0,
    0.24203822016716003,
    0.0,
    0.3899061977863312,
    0.504428505897522,
    0.6490020751953125,
    0.7227112650871277,
    0.5623648166656494,
    0.6626415252685547,
    0.42553192377090454,
    0.35984206199645996,
    0.3412500023841858,
    0.4297029674053192,
    0.5685714483261108,
    0.41995173692703247,
    0.3400673270225525,
    0.13959085941314697,
    0.6107854843139648,
    0.6963755488395691,
    0.54666668176651,
    0.5877094864845276,
    0.451272189617157,
    0.3403441607952118,
    0.433382123708725,
    0.7841269969940186,
    0.29750144481658936,
    0.5614035129547119,
    0.02678571455180645,
    0.5016722679138184,
    0.22067363560199738,
    0.07907743006944656
  ],
  "mean_dice": 0.4386785924434662,
  "head_checkpoint_sha256": "e86ade3c36dc20e4e04d3138804a5fed965fa213ff0266a1258f222bbf475617",
  "training_elapsed_s": 480.14825773239136,
  "use_amp_bf16": true,
  "input_hw": [
    224,
    224
  ],
  "loss_type": "dice_plus_bce",
  "augment": "hflip+rot15_reflection",
  "resolution_note": "M14 spec requested 336 but frozen encoders in fmpool.encoders require 224 (DINOv2/CLIP/CNN positional encodings hard-asserted to a 16x16 or 7x7 patch grid). INPUT_HW retained at 224.",
  "schema_version": "m14_clinical_v1"
}